setup.py
kong_cli.egg-info/PKG-INFO
kong_cli.egg-info/SOURCES.txt
kong_cli.egg-info/dependency_links.txt
kong_cli.egg-info/requires.txt
kong_cli.egg-info/top_level.txt
kongcli/__init__.py
kongcli/core.py
script/kong-cli