Metadata-Version: 1.0
Name: kong-cli
Version: 0.10.1
Summary: A command line client tools for Kong (http://getkong.org)
Home-page: https://github.com/passos/kong-cli
Author: Simon / Jinyu LIU
Author-email: simon.jinyu.liu@gmail.com
License: Apache
Platform: UNKNOWN
